{
  "title": "AdventureLog LXC",
  "category": "Miscellaneous",
  "imgSrc": "https://raw.githubusercontent.com/seanmorley15/AdventureLog/refs/heads/main/documentation/static/img/favicon.png",
  "scripts": [
    "https://github.com/community-scripts/ProxmoxVE/raw/main/ct/adventurelog.sh"
  ],
  "textContent": "\n                \n                 AdventureLog LXC \n                AdventureLog\n                    Discover\n                    and plan your next adventure with AdventureLog. Explore breathtaking destinations, create custom\n                    itineraries, and stay connected on the go.\n                To create a new Proxmox VE AdventureLog LXC, run the following in the Proxmox VE Shell.\n                    To Update AdventureLog, run the command below (or type update) in the LXC Console.\n                Copybash -c \"$(wget -qLO - https://github.com/community-scripts/ProxmoxVE/raw/main/ct/adventurelog.sh)\"\n                ⚡ Default Settings: 2GB RAM - 7GB Storage - 2vCPU ⚡\n                AdventureLog Interface - IP:3000\n            ",
  "outerHTML": "<div class=\"item\">\n                <p align=\"center\"><img src=\"https://raw.githubusercontent.com/seanmorley15/AdventureLog/refs/heads/main/documentation/static/img/favicon.png \" height=\"100\"></p>\n                <h1 align=\"center\" id=\"heading\"> AdventureLog LXC </h1>\n                <p><a href=\"https://adventurelog.app/\" target=\"_blank\" rel=\"noopener noreferrer\">AdventureLog</a>\n                    Discover\n                    and plan your next adventure with AdventureLog. Explore breathtaking destinations, create custom\n                    itineraries, and stay connected on the go.</p>\n                <p>To create a new Proxmox VE AdventureLog LXC, run the following in the <b>Proxmox VE Shell</b>.<br>\n                    To Update AdventureLog, run the command below (or type update) in the <b>LXC Console</b>.</p>\n                <pre><button class=\"copy-button \">Copy</button><div style=\"color: rgb(227, 234, 242); background: rgb(17, 27, 39); font-family: Consolas, Monaco, &quot;Andale Mono&quot;, &quot;Ubuntu Mono&quot;, monospace; text-align: left; white-space: pre; word-spacing: normal; word-break: normal; overflow-wrap: normal; line-height: 1.5; tab-size: 4; hyphens: none; padding: 1em; margin: 0.5em 0px; overflow: auto;\"><code class=\"language-bash\" style=\"color: rgb(227, 234, 242); background: none; font-family: Consolas, Monaco, &quot;Andale Mono&quot;, &quot;Ubuntu Mono&quot;, monospace; text-align: left; white-space: pre; word-spacing: normal; word-break: normal; overflow-wrap: normal; line-height: 1.5; tab-size: 4; hyphens: none;\"><span class=\"token\" style=\"color: rgb(198, 153, 227);\">bash</span><span> -c </span><span class=\"token\" style=\"color: rgb(145, 208, 118);\">\"</span><span class=\"token\" style=\"color: rgb(108, 184, 230);\">$(</span><span class=\"token\" style=\"color: rgb(198, 153, 227);\">wget</span><span class=\"token\" style=\"color: rgb(108, 184, 230);\"> -qLO - https://github.com/community-scripts/ProxmoxVE/raw/main/ct/adventurelog.sh</span><span class=\"token\" style=\"color: rgb(108, 184, 230);\">)</span><span class=\"token\" style=\"color: rgb(145, 208, 118);\">\"</span></code></div></pre>\n                <h3 align=\"center\" id=\"heading\">⚡ Default Settings: 2GB RAM - 7GB Storage - 2vCPU ⚡</h3>\n                <p><strong>AdventureLog Interface - IP:3000</strong></p>\n            </div>",
  "ports": [
    "3000"
  ]
}